README.rst
setup.py
libbgp/__init__.py
libbgp/exception.py
libbgp/flag.py
libbgp/tlv.py
libbgp.egg-info/PKG-INFO
libbgp.egg-info/SOURCES.txt
libbgp.egg-info/dependency_links.txt
libbgp.egg-info/top_level.txt
libbgp/bgp/__init__.py
libbgp/bgp/ciscorouterefresh.py
libbgp/bgp/keepalive.py
libbgp/bgp/message.py
libbgp/bgp/notification.py
libbgp/bgp/routerefresh.py
libbgp/bgp/open/__init__.py
libbgp/bgp/open/capability/__init__.py
libbgp/bgp/open/capability/as4.py
libbgp/bgp/open/capability/capabilities.py
libbgp/bgp/open/capability/capability.py
libbgp/bgp/open/capability/ciscorouterefresh.py
libbgp/bgp/open/capability/multiprotocol.py
libbgp/bgp/open/capability/routerefresh.py
libbgp/bgp/update/__init__.py
libbgp/bgp/update/attribute/__init__.py
libbgp/bgp/update/attribute/aggregator.py
libbgp/bgp/update/attribute/aspath.py
libbgp/bgp/update/attribute/atomicaggregate.py
libbgp/bgp/update/attribute/attribute.py
libbgp/bgp/update/attribute/attributes.py
libbgp/bgp/update/attribute/clusterlist.py
libbgp/bgp/update/attribute/localpref.py
libbgp/bgp/update/attribute/med.py
libbgp/bgp/update/attribute/nexthop.py
libbgp/bgp/update/attribute/origin.py
libbgp/bgp/update/attribute/originatorid.py
libbgp/bgp/update/attribute/community/__init__.py
libbgp/bgp/update/attribute/community/rfc1997/__init__.py
libbgp/bgp/update/attribute/community/rfc1997/communities.py
libbgp/bgp/update/attribute/community/rfc4360/__init__.py
libbgp/bmp/__init__.py
libbgp/bmp/initiation.py
libbgp/bmp/message.py
libbgp/bmp/peer_down.py
libbgp/bmp/peer_up.py
libbgp/bmp/route_monitor.py
libbgp/bmp/stats_report.py
libbgp/bmp/termination.py
libbgp/net/__init__.py
libbgp/net/family.py
libbgp/tests/__init__.py
libbgp/tests/unit/__init__.py
libbgp/tests/unit/test_flags.py
libbgp/tests/unit/bgp/__init__.py
libbgp/tests/unit/bgp/test_keepalive.py
libbgp/tests/unit/bgp/test_notification.py
libbgp/tests/unit/bgp/test_routerefresh.py
libbgp/tests/unit/bgp/test_update.py
libbgp/tests/unit/bgp/attribute/__init__.py
libbgp/tests/unit/bgp/attribute/test_aggregator.py
libbgp/tests/unit/bgp/attribute/test_aspath.py
