Metadata-Version: 1.1
Name: libbgp
Version: 0.2.0
Summary: Python BGP/BMP Message parser lib
Home-page: https://github.com/smartbgp/libbgp
Author: Peng Xiao
Author-email: xiaoquwl@gmail.com
License: Apache 2.0
Keywords: BGP BMP Python
Platform: any
Classifier: Development Status :: 5 - Production/Stable
Classifier: Environment :: Web Environment
Classifier: Intended Audience :: Developers
Classifier: License :: OSI Approved :: Apache Software License
Classifier: Operating System :: OS Independent
Classifier: Programming Language :: Python
Classifier: Programming Language :: Python :: 2
Classifier: Programming Language :: Python :: 2.7
